{
  "display": {
	"icon": {
	  "id": "kamenridercraft:gashacon_bugvisor_ii_poppy"
	},
	"title": {
      "translate": "advancements.kamenridercraft.ex-aid.poppy.title"
    },
    "description": {
      "translate": "advancements.kamenridercraft.ex-aid.poppy.description"
    },
    "frame": "task",
	"show_toast": true,
	"announce_to_chat": true,
	"hidden": false
  },
  "parent": "kamenridercraft:ex-aid/genm",
  "criteria": {
	"requirement": {
      "trigger": "minecraft:player_killed_entity",
      "conditions": {
        "entity": {
          "type": "kamenridercraft:poppy_red_mob"
        }
      }
    }
  }
}
