{
	"name": "Trooper Kuwagata Vistamp",
	"icon": "kamenridercraft:kuwagata_trooper_vistamp",
	"category": "kamenridercraft:revice/items",
	"sortnum": 50,
	"pages": [
		{
			"type": "patchouli:text",
			"text": "Appears in:$(li)Kamen Rider Revice (2021, TV show)$(br2)Used to craft Demons Trooper b's $(l:revice/devices/demons_driver_demons_trooper_b)Demons Driver (Trooper b)$(/l)"
		},
		{
			"type": "patchouli:spotlight",
			"link_recipe": true,
			"item": "kamenridercraft:kuwagata_trooper_vistamp",
			"title": " ",
			"text": "Item is currently unobtainable"
		}
	]
}