{
  "type": "minecraft:entity",
  "pools": [
    {
      "rolls": 1,
      "entries": [
        {
          "type": "minecraft:item",
          "name": "kamenridercraft:blank_progrisekey",
          "functions": [
            {
              "function": "minecraft:set_count",
              "count": {
                "min": 0,
                "max": 2
              }
            }
          ]
        }
      ]
    },
    {
      "rolls": 1,
      "entries": [
        {
          "type": "minecraft:item",
          "name": "kamenridercraft:mammoth_zetsumerisekey"
        },
        {
          "type": "minecraft:item",
          "name": "kamenridercraft:breaking_mammoth_progrisekey"
        }
      ]
    }
  ]
}
