{
	"name": "Thousand Ark Progrisekey",
	"icon": "kamenridercraft:thousand_ark_progrisekey",
	"category": "kamenridercraft:zero_one/items",
	"sortnum": 44,
	"pages": [
		{
			"type": "patchouli:text",
			"text": "Appears in:$(li)Kamen Rider Genms -Smart Brain and the 1000% Crisis- (2022, TTFC special)$(br2)Used to craft Thousand Ark's $(l:zero_one/devices/ark_driver_zero_thousand_ark)Ark Driver-Zero (Thousand Ark)$(/l)"
		},
		{
			"type": "patchouli:crafting",
			"recipe": "kamenridercraft:zero_one/thousand_ark_progrisekey"
		}
	]
}