{
  "name": "kamenridercraft:shockerbase/hallways",
  
  "fallback": "minecraft:empty",
  "elements": [{
    "weight": 1,
    "element": {
      "location": "kamenridercraft:shockerbase/start_room",
      "processors": "minecraft:empty",
      "projection": "rigid",
      "element_type": "minecraft:single_pool_element"
    }
  },{
    "weight": 1,
    "element": {
      "location": "kamenridercraft:shockerbase/hallways/hallway_to_steps",
      "processors": "minecraft:empty",
      "projection": "rigid",
      "element_type": "minecraft:single_pool_element"
    }
  },{
    "weight": 1,
    "element": {
      "location": "kamenridercraft:shockerbase/hallways/hallway_to_steps_2nd",
      "processors": "minecraft:empty",
      "projection": "rigid",
      "element_type": "minecraft:single_pool_element"
    }
  },{
    "weight": 1,
    "element": {
      "location": "kamenridercraft:shockerbase/hallways/hallway_end_with_steps",
      "processors": "minecraft:empty",
      "projection": "rigid",
      "element_type": "minecraft:single_pool_element"
    }
  },{
    "weight": 1,
    "element": {
      "location": "kamenridercraft:shockerbase/hallways/start_room_2nd_floor",
      "processors": "minecraft:empty",
      "projection": "rigid",
      "element_type": "minecraft:single_pool_element"
    }
  },
    {
      "weight": 1,
      "element": {
        "location": "kamenridercraft:shockerbase/hallways/hallway",
        "processors": "minecraft:empty",
        "projection": "rigid",
        "element_type": "minecraft:single_pool_element"
      }
    },
    {
      "weight": 1,
      "element": {
        "location": "kamenridercraft:shockerbase/hallways/hallway_alt1",
        "processors": "minecraft:empty",
        "projection": "rigid",
        "element_type": "minecraft:single_pool_element"
      }
    },
    {
      "weight": 1,
      "element": {
        "location": "kamenridercraft:shockerbase/hallways/hallway_alt2",
        "processors": "minecraft:empty",
        "projection": "rigid",
        "element_type": "minecraft:single_pool_element"
      }
    },
    {
      "weight": 1,
      "element": {
        "location": "kamenridercraft:shockerbase/hallways/hallway_alt3",
        "processors": "minecraft:empty",
        "projection": "rigid",
        "element_type": "minecraft:single_pool_element"
      }
    },{
      "weight": 1,
      "element": {
        "location": "kamenridercraft:shockerbase/hallways/hallway_out_l",
        "processors": "minecraft:empty",
        "projection": "rigid",
        "element_type": "minecraft:single_pool_element"
      }
    },{
      "weight": 1,
      "element": {
        "location": "kamenridercraft:shockerbase/hallways/hallway_out_r",
        "processors": "minecraft:empty",
        "projection": "rigid",
        "element_type": "minecraft:single_pool_element"
      }
    },{
      "weight": 1,
      "element": {
        "location": "kamenridercraft:shockerbase/hallways/outer_corner",
        "processors": "minecraft:empty",
        "projection": "rigid",
        "element_type": "minecraft:single_pool_element"
      }
    },{
      "weight": 1,
      "element": {
        "location": "kamenridercraft:shockerbase/hallways/outer_t",
        "processors": "minecraft:empty",
        "projection": "rigid",
        "element_type": "minecraft:single_pool_element"
      }
    }
  ]
}