{
	"name": "Kamen Rider Shion",
	"icon": "kamenridercraft:chaos_driver_shion",
	"category": "kamenridercraft:ride_kamens/riders",
	"sortnum": 2,
	"pages": [
		{
			"type": "patchouli:entity",
			"entity": "kamenridercraft:shocker_combatman{ArmorItems:[{id:\"kamenridercraft:chaos_driver_shion\",Count:1b},{id:\"kamenridercraft:ride_kamens_legs\",Count:1b},{id:\"kamenridercraft:ride_kamens_troso\",Count:1b},{id:\"kamenridercraft:ride_kamens_head\",Count:1b}]}",
			"name": " ",
			"text": ""
		},
		{
			"type": "patchouli:text",
			"title": "Kamen Rider Shion",
			"text": "Appears in:$(li)Ride Kamens (2024, mobile game)$(br2)Transforms with the $(l:ride_kamens/devices/chaos_driver_shion)Chaos Driver (Shion)$(/l)$(br2)Status Effects:$(li)Punch II$(li)Haste$(li)Jump Boost II$(li)Strength V (with empty hand)$(li)Strength II (with weapon)"
		}
	]
}