{
	"name": "Unknown Wizard Ring",
	"icon": "kamenridercraft:unknown_violet_ring",
	"category": "kamenridercraft:wizard/items",
	"sortnum": 68,
	"pages": [
		{
			"type": "patchouli:text",
			"text": "Appears in:$(li)Kamen Rider Wizard (2012, TV show)$(br2)Drops $(l:wizard/arsenal/explosion_ring)Wizard Rings$(/l) when obtained$(br2)Drops:$(li)$(l:wizard/items/dark_ring)Dark Wizard Ring$(/l) (20%)$(li)$(l:wizard/items/explosion_ring)Explosion Wizard Ring$(/l) (20%)$(li)$(l:wizard/items/teleport_ring)Teleport Wizard Ring$(/l) (20%)$(li)$(l:wizard/items/eclipse_ring)Eclipse Wizard Ring$(/l) (20%)$(li)$(l:wizard/items/golem_ring)Golem Wizard Ring$(/l) (20%)"
		},
		{
			"type": "patchouli:crafting",
			"recipe": "kamenridercraft:wizard/unknown_violet_ring"
		}
	]
}