{
	"name": "Popburn Gochizo",
	"icon": "kamenridercraft:popburn_gochizo",
	"category": "kamenridercraft:gavv/items",
	"sortnum": 22,
	"pages": [
		{
			"type": "patchouli:text",
			"text": "Appears in:$(li)DX Popburn Gochizo (2024, toyline)"
		},
		{
			"type": "patchouli:spotlight",
			"link_recipe": true,
			"item": "kamenridercraft:popburn_gochizo",
			"title": " ",
			"text": "Obtained by eating $(l:misc/items/potato_snacks)Potato Snacks$(/l) with a $(l:gavv/items/blank_gochizo)Blank Gochizo$(/l) in your inventory"
		}
	]
}