{
  "display": {
	"icon": {
	  "id": "kamenridercraft:sclash_driver_grease"
	},
	"title": {
      "translate": "advancements.kamenridercraft.build.grease.title"
    },
    "description": {
      "translate": "advancements.kamenridercraft.build.grease.description"
    },
    "frame": "task",
	"show_toast": true,
	"announce_to_chat": true,
	"hidden": false
  },
  "parent": "kamenridercraft:build/cross-z",
  "criteria": {
	"requirement": {
	  "trigger": "minecraft:inventory_changed",
	  "conditions": {
		"player": {
		  "equipment": {
			"head": {
			  "items": [
				"kamenridercraft:buildhead"
			  ]
			},
			"chest": {
			  "items": [
				"kamenridercraft:buildtroso"
			  ]
			},
			"legs": {
			  "items": [
				"kamenridercraft:buildlegs"
			  ]
			},
			"feet": {
			  "items": [
				"kamenridercraft:sclash_driver_grease"
			  ]
			}
		  }
		}
	  }
	}
  }
}
