{
	"format_version": "1.8.0",
	"animations": {
		"mage_captain.pose": {
			"loop": true,
			"bones": {
				"body": {
					"rotation": [0, -28, 0],
					"position": [0, -0.25, 0]
				},
				"torso": {
					"rotation": [-3, 0, 3],
					"position": [1, 0, 1]
				},
				"left_leg": {
					"rotation": [8, -27, -2]
				},
				"right_leg": {
					"rotation": [0, 23, 0],
					"position": [-1, 0, -1]
				},
				"head": {
					"rotation": [0, 25, 0]
				},
				"right_arm": {
					"rotation": [4, 17, 86],
					"position": [-1, -1, 0]
				},
				"left_arm": {
					"rotation": [-69, -15, -3]
				}
			}
		}
	}
}