{
	"format_version": "1.8.0",
	"animations": {
		"meteor.pose": {
			"loop": true,
			"bones": {
				"body": {
					"rotation": [-8, -48, 0]
				},
				"torso": {
					"rotation": [-2, 0, 5]
				},
				"left_leg": {
					"rotation": [40, -20, -16]
				},
				"right_leg": {
					"rotation": [0, 15, 0]
				},
				"head": {
					"rotation": [10, 45, 4],
					"position": [0, 0, -1]
				},
				"right_arm": {
					"rotation": [19, 24, 27]
				},
				"left_arm": {
					"rotation": [-29, 7, -67]
				}
			}
		}
	}
}