{
	"format_version": "1.8.0",
	"animations": {
		"revi.pose": {
			"loop": "hold_on_last_frame",
			"bones": {
				"body": {
					"rotation": [0, -45, 0],
					"position": [0, -1, 0]
				},
				"torso": {
					"rotation": [-8, 0, 3],
					"position": [0, 0, 1]
				},
				"left_leg": {
					"rotation": [5, -30, 0],
					"position": [2, 0, -1]
				},
				"right_leg": {
					"rotation": [6, 37, 9]
				},
				"head": {
					"rotation": [-2, 42, -3]
				},
				"right_arm": {
					"rotation": [1, 7, 8]
				},
				"left_arm": {
					"rotation": [-75, -49, -12],
					"position": [1, 0, -2]
				}
			}
		}
	}
}